{"card_name": "Deadwood Terror", "color": "B", "rarity": "rare", "type": "Creature \u2013 Zombie", "number": 49, "color_identity": "B", "cost": "{1}{B}", "rules_text": "Deathtouch\nWhen Deadwood Terror enters the battlefield from a graveyard, create two tokens that are copies of it.\n{4}{B}{B}, Sacrifice a creature: Return Deadwood Terror from your graveyard to the battlefield. Activate this ability only any time you could cast a sorcery.", "flavor_text": "[i][/i]", "pt": "2/2", "special_text": "", "shape": "normal", "set": "LAW", "loyalty": "", "artist": "Stefan Koidl", "notes": "", "image_type": "png"}