{"card_name": "Reason Rots, Rage Remains", "color": "R", "rarity": "uncommon", "type": "Sorcery", "number": 77, "color_identity": "R", "cost": "{X}{R}{R}", "rules_text": "Reconstruct {X}{R}{R} [i](You may cast this from your graveyard for its reconstruct cost reduced by the converted mana cost of a permanent you sacrifice as you cast it this way. Then exile this.)[/i]\nReason Rots, Rage Remains deals X damage to any target.", "flavor_text": "[i][/i]", "pt": "", "special_text": "", "shape": "normal", "set": "LAW", "loyalty": "", "artist": "Benjamin Ee", "notes": "URNgeneric", "image_type": "png"}