{"card_name": "Raiaton, Realmborn Advocate", "color": "W", "rarity": "rare", "type": "Legendary Creature \u2013 Human Cleric", "number": 14, "color_identity": "W", "cost": "{1}{W}{W}", "rules_text": "Elementals you control get +1/+1 and have ward {1}.\nAt the beginning of your end step, create a 0/0 colorless Elemental creature token.", "flavor_text": "[i]\u201cThere is always room for more life.\u201d[/i]", "pt": "2/3", "special_text": "", "shape": "normal", "set": "KLC2", "loyalty": "", "artist": "Toyin \"Morby\" Ajetunmobi", "notes": "!Veronia", "image_type": "png"}