{"card_name": "Lifecraft Subjects", "color": "B", "rarity": "uncommon", "type": "Creature \u2013 Human Mutant", "number": 53, "color_identity": "B", "cost": "{3}{B}{B}", "rules_text": "When this creature enters, create two 1/1 black Mutant creature tokens with lifelink.\nMutants you control can't block and can't be blocked.", "flavor_text": "[i]Subject by subject, Rheila's knowledge of life and death grew \u2014 and the solace drowned out both their suffering and his conscience.[/i]", "pt": "2/2", "special_text": "", "shape": "normal", "set": "KLC2", "loyalty": "", "artist": "NanFe", "notes": "!tag:Vasille\n!tag:Rheila", "image_type": "png"}